{
  "version": "7",
  "dialect": "sqlite",
  "entries": [
    {
      "idx": 0,
      "version": "6",
      "when": 1728940474585,
      "tag": "0000_condemned_shotgun",
      "breakpoints": true
    },
    {
      "idx": 1,
      "version": "6",
      "when": 1728940723390,
      "tag": "0001_bored_marvel_apes",
      "breakpoints": true
    },
    {
      "idx": 2,
      "version": "6",
      "when": 1729652639539,
      "tag": "0002_shallow_victor_mancha",
      "breakpoints": true
    },
    {
      "idx": 3,
      "version": "6",
      "when": 1730075843761,
      "tag": "0003_flashy_lizard",
      "breakpoints": true
    },
    {
      "idx": 4,
      "version": "6",
      "when": 1732845796838,
      "tag": "0004_lying_ser_duncan",
      "breakpoints": true
    },
    {
      "idx": 5,
      "version": "6",
      "when": 1736812239409,
      "tag": "0005_wide_ezekiel",
      "breakpoints": true
    },
    {
      "idx": 6,
      "version": "6",
      "when": 1736990724746,
      "tag": "0006_busy_nuke",
      "breakpoints": true
    },
    {
      "idx": 7,
      "version": "6",
      "when": 1737165094457,
      "tag": "0007_chemical_hairball",
      "breakpoints": true
    },
    {
      "idx": 8,
      "version": "6",
      "when": 1737165418718,
      "tag": "0008_broad_stephen_strange",
      "breakpoints": true
    },
    {
      "idx": 9,
      "version": "6",
      "when": 1737405479413,
      "tag": "0009_lazy_paibok",
      "breakpoints": true
    },
    {
      "idx": 10,
      "version": "6",
      "when": 1737405983577,
      "tag": "0010_keen_thundra",
      "breakpoints": true
    },
    {
      "idx": 11,
      "version": "6",
      "when": 1737432060146,
      "tag": "0011_absurd_amphibian",
      "breakpoints": true
    },
    {
      "idx": 12,
      "version": "6",
      "when": 1738283148715,
      "tag": "0012_tranquil_franklin_richards",
      "breakpoints": true
    },
    {
      "idx": 13,
      "version": "6",
      "when": 1743983696723,
      "tag": "0013_thick_jack_murdock",
      "breakpoints": true
    },
    {
      "idx": 14,
      "version": "6",
      "when": 1745454066853,
      "tag": "0014_silent_pretty_boy",
      "breakpoints": true
    },
    {
      "idx": 15,
      "version": "6",
      "when": 1745685738235,
      "tag": "0015_worried_king_bedlam",
      "breakpoints": true
    },
    {
      "idx": 16,
      "version": "6",
      "when": 1745690970293,
      "tag": "0016_remarkable_pete_wisdom",
      "breakpoints": true
    },
    {
      "idx": 17,
      "version": "6",
      "when": 1746794610796,
      "tag": "0017_unique_toad_men",
      "breakpoints": true
    },
    {
      "idx": 18,
      "version": "6",
      "when": 1747760102597,
      "tag": "0018_smart_lilandra",
      "breakpoints": true
    },
    {
      "idx": 19,
      "version": "6",
      "when": 1747940012550,
      "tag": "0019_tan_kronos",
      "breakpoints": true
    },
    {
      "idx": 20,
      "version": "6",
      "when": 1748575525243,
      "tag": "0020_tricky_vermin",
      "breakpoints": true
    },
    {
      "idx": 21,
      "version": "6",
      "when": 1762133216320,
      "tag": "0021_blue_thanos",
      "breakpoints": true
    }
  ]
}